README.md
setup.py
litsr/__init__.py
litsr/version.py
litsr.egg-info/PKG-INFO
litsr.egg-info/SOURCES.txt
litsr.egg-info/dependency_links.txt
litsr.egg-info/not-zip-safe
litsr.egg-info/requires.txt
litsr.egg-info/top_level.txt
litsr/archs/__init__.py
litsr/archs/common.py
litsr/archs/edsr_arch.py
litsr/archs/rdn_arch.py
litsr/data/__init__.py
litsr/data/degradations.py
litsr/data/downsampled_dataset.py
litsr/data/image_folder.py
litsr/data/paired_image_dataset.py
litsr/data/realesrgan_dataset.py
litsr/data/realsr_datamodule.py
litsr/data/single_image_dataset.py
litsr/data/sr_datamodule.py
litsr/losses/__init__.py
litsr/metrics/__init__.py
litsr/metrics/fid.py
litsr/metrics/psnr_ssim.py
litsr/models/__init__.py
litsr/models/multiscale_sr_model.py
litsr/models/realesrnet_model.py
litsr/models/sr_model.py
litsr/models/utils.py
litsr/transforms/__init__.py
litsr/transforms/data_funcs.py
litsr/transforms/matlab_funcs.py
litsr/utils/__init__.py
litsr/utils/diffjpeg.py
litsr/utils/diffusion.py
litsr/utils/img_utils.py
litsr/utils/io_utils.py
litsr/utils/registry.py